<annotation>
	<folder>images</folder>
	<filename>10231.jpg</filename>
	<path>G:\数据集\Asoul\images\10231.jpg</path>
	<source>
		<database>Unknown</database>
	</source>
	<size>
		<width>1280</width>
		<height>720</height>
		<depth>3</depth>
	</size>
	<segmented>0</segmented>
	<object>
		<name>Diana</name>
		<pose>Unspecified</pose>
		<truncated>0</truncated>
		<difficult>0</difficult>
		<bndbox>
			<xmin>241</xmin>
			<ymin>260</ymin>
			<xmax>452</xmax>
			<ymax>601</ymax>
		</bndbox>
	</object>
	<object>
		<name>Ava</name>
		<pose>Unspecified</pose>
		<truncated>0</truncated>
		<difficult>0</difficult>
		<bndbox>
			<xmin>473</xmin>
			<ymin>219</ymin>
			<xmax>664</xmax>
			<ymax>598</ymax>
		</bndbox>
	</object>
	<object>
		<name>Bella</name>
		<pose>Unspecified</pose>
		<truncated>0</truncated>
		<difficult>0</difficult>
		<bndbox>
			<xmin>631</xmin>
			<ymin>217</ymin>
			<xmax>820</xmax>
			<ymax>621</ymax>
		</bndbox>
	</object>
	<object>
		<name>Eileen</name>
		<pose>Unspecified</pose>
		<truncated>0</truncated>
		<difficult>0</difficult>
		<bndbox>
			<xmin>857</xmin>
			<ymin>234</ymin>
			<xmax>1071</xmax>
			<ymax>602</ymax>
		</bndbox>
	</object>
</annotation>
