<annotation>
	<folder>images</folder>
	<filename>2751.jpg</filename>
	<path>G:\数据集\Asoul\images\2751.jpg</path>
	<source>
		<database>Unknown</database>
	</source>
	<size>
		<width>1280</width>
		<height>720</height>
		<depth>3</depth>
	</size>
	<segmented>0</segmented>
	<object>
		<name>Eileen</name>
		<pose>Unspecified</pose>
		<truncated>0</truncated>
		<difficult>0</difficult>
		<bndbox>
			<xmin>607</xmin>
			<ymin>345</ymin>
			<xmax>688</xmax>
			<ymax>589</ymax>
		</bndbox>
	</object>
	<object>
		<name>Diana</name>
		<pose>Unspecified</pose>
		<truncated>0</truncated>
		<difficult>0</difficult>
		<bndbox>
			<xmin>777</xmin>
			<ymin>357</ymin>
			<xmax>850</xmax>
			<ymax>542</ymax>
		</bndbox>
	</object>
	<object>
		<name>Carol</name>
		<pose>Unspecified</pose>
		<truncated>0</truncated>
		<difficult>0</difficult>
		<bndbox>
			<xmin>688</xmin>
			<ymin>362</ymin>
			<xmax>772</xmax>
			<ymax>527</ymax>
		</bndbox>
	</object>
	<object>
		<name>Ava</name>
		<pose>Unspecified</pose>
		<truncated>0</truncated>
		<difficult>0</difficult>
		<bndbox>
			<xmin>952</xmin>
			<ymin>353</ymin>
			<xmax>1084</xmax>
			<ymax>596</ymax>
		</bndbox>
	</object>
	<object>
		<name>Bella</name>
		<pose>Unspecified</pose>
		<truncated>0</truncated>
		<difficult>0</difficult>
		<bndbox>
			<xmin>1099</xmin>
			<ymin>344</ymin>
			<xmax>1237</xmax>
			<ymax>623</ymax>
		</bndbox>
	</object>
</annotation>
