<annotation>
	<folder>images</folder>
	<filename>2961.jpg</filename>
	<path>G:\数据集\Asoul\images\2961.jpg</path>
	<source>
		<database>Unknown</database>
	</source>
	<size>
		<width>1280</width>
		<height>720</height>
		<depth>3</depth>
	</size>
	<segmented>0</segmented>
	<object>
		<name>Diana</name>
		<pose>Unspecified</pose>
		<truncated>0</truncated>
		<difficult>0</difficult>
		<bndbox>
			<xmin>786</xmin>
			<ymin>362</ymin>
			<xmax>869</xmax>
			<ymax>562</ymax>
		</bndbox>
	</object>
	<object>
		<name>Eileen</name>
		<pose>Unspecified</pose>
		<truncated>0</truncated>
		<difficult>0</difficult>
		<bndbox>
			<xmin>616</xmin>
			<ymin>342</ymin>
			<xmax>693</xmax>
			<ymax>590</ymax>
		</bndbox>
	</object>
	<object>
		<name>Bella</name>
		<pose>Unspecified</pose>
		<truncated>0</truncated>
		<difficult>0</difficult>
		<bndbox>
			<xmin>1108</xmin>
			<ymin>343</ymin>
			<xmax>1221</xmax>
			<ymax>632</ymax>
		</bndbox>
	</object>
	<object>
		<name>Ava</name>
		<pose>Unspecified</pose>
		<truncated>0</truncated>
		<difficult>0</difficult>
		<bndbox>
			<xmin>961</xmin>
			<ymin>356</ymin>
			<xmax>1101</xmax>
			<ymax>591</ymax>
		</bndbox>
	</object>
	<object>
		<name>Carol</name>
		<pose>Unspecified</pose>
		<truncated>0</truncated>
		<difficult>0</difficult>
		<bndbox>
			<xmin>694</xmin>
			<ymin>351</ymin>
			<xmax>797</xmax>
			<ymax>576</ymax>
		</bndbox>
	</object>
</annotation>
